hebcal_api/__init__.py
hebcal_api/calendar.py
hebcal_api/config.py
hebcal_api/converter.py
hebcal_api/helpers.py
hebcal_api/leyning.py
hebcal_api/shabat.py
hebcal_api/yahrzeit.py
hebcal_api/zmanim.py
hebcal_api/tools/__init__.py
hebcal_api/tools/calendar_formatter.py
hebcal_api/tools/exception.py
hebcal_api/tools/logger.py
hebcal_api/tools/types.py
hebcal_api/tools/utils.py
hebcal_api-0.1.6.dist-info/licenses/LICENSE
hebcal_api-0.1.6.dist-info/METADATA
hebcal_api-0.1.6.dist-info/WHEEL
hebcal_api-0.1.6.dist-info/top_level.txt
hebcal_api-0.1.6.dist-info/RECORD
