Metadata-Version: 2.4
Name: hebcal-api
Version: 0.1.6
Summary: Async client for Hebcal API
Author-email: sudo-py-dev <sudopydev@gmail.com>
License-Expression: MIT
Project-URL: Homepage, https://github.com/sudo-py-dev/hebcal-api
Project-URL: Issues, https://github.com/sudo-py-dev/hebcal-api/issues
Requires-Python: >=3.9
License-File: LICENSE
Requires-Dist: httpx>=0.28.1
Requires-Dist: requests>=2.32.5
Provides-Extra: dev
Requires-Dist: pytest>=7.0.0; extra == "dev"
Requires-Dist: pytest-asyncio>=0.21.0; extra == "dev"
Requires-Dist: pytest-cov>=4.0.0; extra == "dev"
Dynamic: license-file
